[
	{
		"id": "167915",
		"updated_time": "2022-07-28 00:51:28",
		"representative_time": "2022-07-28T00:00:00.000Z",
		"token_1": "EOS",
		"token_2": "TLOS",
		"price_1": "1.24322",
		"price_2": "0.185224"
	},
	{
		"id": "168055",
		"updated_time": "2022-07-28 02:50:13",
		"representative_time": "2022-07-28T02:00:00.000Z",
		"token_1": "EOS",
		"token_2": "TLOS",
		"price_1": "1.26409",
		"price_2": "0.186176"
	},
	{
		"id": "168083",
		"updated_time": "2022-07-28 03:47:30",
		"representative_time": "2022-07-28T03:00:00.000Z",
		"token_1": "EOS",
		"token_2": "TLOS",
		"price_1": "1.26409",
		"price_2": "0.186176"
	},
	{
		"id": "168111",
		"updated_time": "2022-07-28 04:01:21",
		"representative_time": "2022-07-28T04:00:00.000Z",
		"token_1": "EOS",
		"token_2": "TLOS",
		"price_1": "1.26409",
		"price_2": "0.186176"
	},
	{
		"id": "168139",
		"updated_time": "2022-07-28 05:07:56",
		"representative_time": "2022-07-28T05:00:00.000Z",
		"token_1": "EOS",
		"token_2": "TLOS",
		"price_1": "1.26409",
		"price_2": "0.186176"
	},
	{
		"id": "168363",
		"updated_time": "2022-07-28 07:58:20",
		"representative_time": "2022-07-28T07:00:00.000Z",
		"token_1": "EOS",
		"token_2": "TLOS",
		"price_1": "1.26719",
		"price_2": "0.186632"
	},
	{
		"id": "168615",
		"updated_time": "2022-07-28 08:57:51",
		"representative_time": "2022-07-28T08:00:00.000Z",
		"token_1": "EOS",
		"token_2": "TLOS",
		"price_1": "1.27437",
		"price_2": "0.186632"
	},
	{
		"id": "168727",
		"updated_time": "2022-07-28 09:21:43",
		"representative_time": "2022-07-28T09:00:00.000Z",
		"token_1": "EOS",
		"token_2": "TLOS",
		"price_1": "1.27258",
		"price_2": "0.186632"
	},
	{
		"id": "168783",
		"updated_time": "2022-07-28 10:06:25",
		"representative_time": "2022-07-28T10:00:00.000Z",
		"token_1": "EOS",
		"token_2": "TLOS",
		"price_1": "1.27258",
		"price_2": "0.186632"
	},
	{
		"id": "168811",
		"updated_time": "2022-07-28 11:32:39",
		"representative_time": "2022-07-28T11:00:00.000Z",
		"token_1": "EOS",
		"token_2": "TLOS",
		"price_1": "1.27258",
		"price_2": "0.186632"
	},
	{
		"id": "169091",
		"updated_time": "2022-07-28 12:50:31",
		"representative_time": "2022-07-28T12:00:00.000Z",
		"token_1": "EOS",
		"token_2": "TLOS",
		"price_1": "1.24945",
		"price_2": "0.184802"
	},
	{
		"id": "169231",
		"updated_time": "2022-07-28 13:57:11",
		"representative_time": "2022-07-28T13:00:00.000Z",
		"token_1": "EOS",
		"token_2": "TLOS",
		"price_1": "1.24942",
		"price_2": "0.184796"
	},
	{
		"id": "169455",
		"updated_time": "2022-07-28 14:59:02",
		"representative_time": "2022-07-28T14:00:00.000Z",
		"token_1": "EOS",
		"token_2": "TLOS",
		"price_1": "1.26979",
		"price_2": "0.184384"
	},
	{
		"id": "170239",
		"updated_time": "2022-07-28 15:58:11",
		"representative_time": "2022-07-28T15:00:00.000Z",
		"token_1": "EOS",
		"token_2": "TLOS",
		"price_1": "1.30465",
		"price_2": "0.187653"
	},
	{
		"id": "170631",
		"updated_time": "2022-07-28 16:57:13",
		"representative_time": "2022-07-28T16:00:00.000Z",
		"token_1": "EOS",
		"token_2": "TLOS",
		"price_1": "1.31306",
		"price_2": "0.188863"
	},
	{
		"id": "171163",
		"updated_time": "2022-07-28 17:47:08",
		"representative_time": "2022-07-28T17:00:00.000Z",
		"token_1": "EOS",
		"token_2": "TLOS",
		"price_1": "1.33654",
		"price_2": "0.190509"
	},
	{
		"id": "171499",
		"updated_time": "2022-07-28 18:59:14",
		"representative_time": "2022-07-28T18:00:00.000Z",
		"token_1": "EOS",
		"token_2": "TLOS",
		"price_1": "1.33654",
		"price_2": "0.190509"
	},
	{
		"id": "171891",
		"updated_time": "2022-07-28 19:55:42",
		"representative_time": "2022-07-28T19:00:00.000Z",
		"token_1": "EOS",
		"token_2": "TLOS",
		"price_1": "1.32112",
		"price_2": "0.188217"
	},
	{
		"id": "172059",
		"updated_time": "2022-07-28 20:47:56",
		"representative_time": "2022-07-28T20:00:00.000Z",
		"token_1": "EOS",
		"token_2": "TLOS",
		"price_1": "1.33996",
		"price_2": "0.19002"
	},
	{
		"id": "172339",
		"updated_time": "2022-07-28 22:25:50",
		"representative_time": "2022-07-28T22:00:00.000Z",
		"token_1": "EOS",
		"token_2": "TLOS",
		"price_1": "1.33996",
		"price_2": "0.19002"
	},
	{
		"id": "172451",
		"updated_time": "2022-07-28 23:33:01",
		"representative_time": "2022-07-28T23:00:00.000Z",
		"token_1": "EOS",
		"token_2": "TLOS",
		"price_1": "1.32648",
		"price_2": "0.188108"
	},
	{
		"id": "172647",
		"updated_time": "2022-07-29 00:29:53",
		"representative_time": "2022-07-29T00:00:00.000Z",
		"token_1": "EOS",
		"token_2": "TLOS",
		"price_1": "1.30572",
		"price_2": "0.187856"
	},
	{
		"id": "172843",
		"updated_time": "2022-07-29 01:57:57",
		"representative_time": "2022-07-29T01:00:00.000Z",
		"token_1": "EOS",
		"token_2": "TLOS",
		"price_1": "1.30523",
		"price_2": "0.187856"
	},
	{
		"id": "173151",
		"updated_time": "2022-07-29 02:55:57",
		"representative_time": "2022-07-29T02:00:00.000Z",
		"token_1": "EOS",
		"token_2": "TLOS",
		"price_1": "1.29562",
		"price_2": "0.187856"
	},
	{
		"id": "173179",
		"updated_time": "2022-07-29 03:36:50",
		"representative_time": "2022-07-29T03:00:00.000Z",
		"token_1": "EOS",
		"token_2": "TLOS",
		"price_1": "1.29562",
		"price_2": "0.187856"
	},
	{
		"id": "173711",
		"updated_time": "2022-07-29 04:58:42",
		"representative_time": "2022-07-29T04:00:00.000Z",
		"token_1": "EOS",
		"token_2": "TLOS",
		"price_1": "1.30762",
		"price_2": "0.187727"
	},
	{
		"id": "173739",
		"updated_time": "2022-07-29 05:25:09",
		"representative_time": "2022-07-29T05:00:00.000Z",
		"token_1": "EOS",
		"token_2": "TLOS",
		"price_1": "1.30762",
		"price_2": "0.187727"
	}
]